airvue_sg/__init__.py
airvue_sg/attachment.py
airvue_sg/boto.py
airvue_sg/gmail.py
airvue_sg/label.py
airvue_sg/message.py
airvue_sg/query.py
airvuesg-0.1.3.dist-info/WHEEL
airvuesg-0.1.3.dist-info/METADATA
airvuesg-0.1.3.dist-info/RECORD
