Metadata-Version: 2.1
Name: airvuesg
Version: 0.1.3
Summary: Library to access Gmail using credentials stored in S3, using boto3
Author: Airvue
Requires-Python: >=3.9,<4.0
Classifier: Programming Language :: Python :: 3
Classifier: Programming Language :: Python :: 3.9
Classifier: Programming Language :: Python :: 3.10
Classifier: Programming Language :: Python :: 3.11
Requires-Dist: beautifulsoup4 (>=4.12.0,<5.0.0)
Requires-Dist: boto3 (>=1.26.96,<2.0.0)
Requires-Dist: google-api-python-client (>=2.82.0,<3.0.0)
Requires-Dist: lxml (>=4.9.2,<5.0.0)
Requires-Dist: oauth2client (>=4.1.3,<5.0.0)
Requires-Dist: python-dateutil (>=2.8.2,<3.0.0)
